<?xml version="1.0" encoding="UTF-8"?>
<record_update table="sp_theme">
    <sp_theme action="INSERT_OR_UPDATE">
        <css_variables/>
        <footer display_value="survey footer">59d0bbb1dbe3e70054d8ff621f9619b4</footer>
        <footer_fixed>true</footer_fixed>
        <header display_value="survey header">295177f1dbe3e70054d8ff621f96194d</header>
        <name>survey theme</name>
        <navbar_fixed>true</navbar_fixed>
        <sys_class_name>sp_theme</sys_class_name>
        <sys_created_by>yuw5@nih.gov</sys_created_by>
        <sys_created_on>2019-02-11 22:07:46</sys_created_on>
        <sys_customer_update>false</sys_customer_update>
        <sys_id>f78e6bfddba3e70054d8ff621f9619a5</sys_id>
        <sys_mod_count>2</sys_mod_count>
        <sys_name>survey theme</sys_name>
        <sys_package display_value="Partnership program process survey" source="x_naci_survey">c3cce779dbeb6b00b86770c08c96191e</sys_package>
        <sys_policy/>
        <sys_replace_on_upgrade>false</sys_replace_on_upgrade>
        <sys_scope display_value="Partnership program process survey">c3cce779dbeb6b00b86770c08c96191e</sys_scope>
        <sys_update_name>sp_theme_f78e6bfddba3e70054d8ff621f9619a5</sys_update_name>
        <sys_updated_by>yuw5@nih.gov</sys_updated_by>
        <sys_updated_on>2019-02-11 22:20:44</sys_updated_on>
    </sp_theme>
</record_update>
